pytemplatecode/__init__.py
pytemplatecode/core.py
PyTemplateCode-0.22.dist-info/METADATA
PyTemplateCode-0.22.dist-info/WHEEL
PyTemplateCode-0.22.dist-info/top_level.txt
PyTemplateCode-0.22.dist-info/RECORD
