Metadata-Version: 2.1
Name: PyTemplateCode
Version: 0.22
Summary: A simple Python template project for beginners with useful functions.
Home-page: https://github.com/KusokMedi/pytemplatecode
Author: KusokMedi
Author-email: matvejs.stepanovs116@gmail.com
Classifier: Programming Language :: Python :: 3
Classifier: License :: OSI Approved :: MIT License
Classifier: Operating System :: OS Independent
Requires-Python: >=3.6
